tap_test_data_generator/__init__.py
tap_test_data_generator/data_generator.py
tap_test_data_generator/string_generator.py
tap_test_data_generator/value_pairs_combinator.py
tap_test_data_generator/metadatas/sample.json
tap_test_data_generator/metadatas/sample2.json
tap_test_data_generator/metadatas/sample3.json
tap_test_data_generator/object-repositories/dim-sample.json
tap_test_data_generator/schemas/sample.json
tap_test_data_generator/schemas/sample2.json
tap_test_data_generator/schemas/sample3.json
tests/__init__.py
tests/test_data_generator.py
tests/test_discovery.py
tests/test_sync.py
tests/value_pairs_combinator.py
tap_test_data_generator-1.4.0.dist-info/LICENSE
tap_test_data_generator-1.4.0.dist-info/METADATA
tap_test_data_generator-1.4.0.dist-info/WHEEL
tap_test_data_generator-1.4.0.dist-info/entry_points.txt
tap_test_data_generator-1.4.0.dist-info/top_level.txt
tap_test_data_generator-1.4.0.dist-info/RECORD
