Metadata-Version: 2.1
Name: tap-test-data-generator
Version: 1.4.0
Summary: Singer.io tap for generating test data
Home-page: https://github.com/ericlebail/tap-test-data-generator
Author: ericlebail
Classifier: Programming Language :: Python :: 3 :: Only
Classifier: License :: OSI Approved :: GNU Affero General Public License v3
Classifier: Operating System :: OS Independent
Requires-Python: >=3.8
License-File: LICENSE
Requires-Dist: singer-python (==5.13.0)
Requires-Dist: setuptools (==65.6.3)
Requires-Dist: importlib-metadata (==5.2.0)
Requires-Dist: requests
Requires-Dist: jsonschema (==2.6.0)
Requires-Dist: Faker (==15.3.4)
Requires-Dist: exrex (==0.10.5)
Requires-Dist: ijson (==3.1.4)
Requires-Dist: allpairspy (==2.5.0)
Provides-Extra: test
Requires-Dist: pytest (==7.2.0) ; extra == 'test'
Requires-Dist: pytest-cov (==4.0.0) ; extra == 'test'
Requires-Dist: pytest-mock (==3.10.0) ; extra == 'test'
Requires-Dist: testfixtures (==7.0.4) ; extra == 'test'
Requires-Dist: coverage (==7.0.1) ; extra == 'test'
